{
  "build-version": "0.0.2",
  "dependencies": {
    "yum": [
      "atlas-devel",
      "blas-devel",
      "lapack-devel",
      "findutils",
      "gcc",
      "gcc-c++"
    ],
    "pypi": [
      ["numpy", ">=1.16,<1.17"]
    ],
    "setup_python": {
      "pipenv": "2018.11.26",
      "python": "3.7.3",
      "home": "/root",
      "workdir": "/tmp"
    }
  },
  "libs": [
    "/usr/lib64/atlas/libtatlas.so.3",
    "/usr/lib64/libquadmath.so.0",
    "/usr/lib64/libgfortran.so.4"
  ],
  "docker": {
    "image": "amazonlinux:2"
  }
}
